LICENSE
README.md
pyproject.toml
setup.cfg
setup.py
pyhdbpp/__init__.py
pyhdbpp/abstract.py
pyhdbpp/check.py
pyhdbpp/reader.py
pyhdbpp/utils.py
pyhdbpp.egg-info/PKG-INFO
pyhdbpp.egg-info/SOURCES.txt
pyhdbpp.egg-info/dependency_links.txt
pyhdbpp.egg-info/entry_points.txt
pyhdbpp.egg-info/requires.txt
pyhdbpp.egg-info/top_level.txt
pyhdbpp/mariadb/__init__.py
pyhdbpp/mariadb/mariadb.py
pyhdbpp/multidb/__init__.py
pyhdbpp/multidb/multidb.py
pyhdbpp/timescaledb/__init__.py
pyhdbpp/timescaledb/timescaledb.py
pyhdbpp/tools/__init__.py
pyhdbpp/tools/hdb2csv.py
pyhdbpp/tools/qt/__init__.py
pyhdbpp/tools/qt/plot.py