Metadata-Version: 2.1
Name: pyhdbpp
Version: 1.7.4
Summary: hdb++ python3 API
Home-page: https://gitlab.com/tango-controls/hdbpp/libhdbpp-python
Author: Sergi Rubio, Damien Lacoste
Author-email: info@tango-controls.org
License: LGPL-3+
Classifier: Programming Language :: Python :: 3
Requires-Python: >=3.5
Provides-Extra: hdb2csv
Provides-Extra: mariadb
Provides-Extra: timescaledb
License-File: LICENSE
